{
  "web_ui": {
    "consecutive_failures": 0,
    "incident_reported": false,
    "last_timestamp": "2026-02-26T09:15:23Z"
  },
  "api": {
    "consecutive_failures": 0,
    "incident_reported": false,
    "last_timestamp": "2026-02-26T09:15:24Z"
  },
  "sandbox": {
    "consecutive_failures": 0,
    "incident_reported": false,
    "last_timestamp": "2026-02-26T09:15:25Z"
  },
  "plugin": {
    "consecutive_failures": 0,
    "incident_reported": false,
    "last_timestamp": "2026-02-26T09:15:50Z"
  },
  "retrieve": {
    "consecutive_failures": 0,
    "incident_reported": false,
    "last_timestamp": "2026-02-26T09:15:55Z"
  },
  "indexing_pro": {
    "consecutive_failures": 13,
    "incident_reported": true,
    "last_timestamp": "2026-02-26T09:01:57Z"
  },
  "webhook_free": {
    "consecutive_failures": 0,
    "incident_reported": false,
    "last_timestamp": "2026-02-26T09:01:57Z"
  },
  "webhook_pro": {
    "consecutive_failures": 0,
    "incident_reported": false,
    "last_timestamp": "2026-02-26T09:01:59Z"
  },
  "indexing_free": {
    "consecutive_failures": 8,
    "incident_reported": true,
    "last_timestamp": "2026-02-26T09:01:40Z"
  }
}