{
  "web_ui": {
    "consecutive_failures": 0,
    "incident_reported": false,
    "last_timestamp": "2026-03-02T10:15:22Z"
  },
  "api": {
    "consecutive_failures": 14,
    "incident_reported": true,
    "last_timestamp": "2026-03-02T10:16:22Z"
  },
  "sandbox": {
    "consecutive_failures": 14,
    "incident_reported": true,
    "last_timestamp": "2026-03-02T10:17:23Z"
  },
  "plugin": {
    "consecutive_failures": 14,
    "incident_reported": true,
    "last_timestamp": "2026-03-02T10:18:23Z"
  },
  "retrieve": {
    "consecutive_failures": 0,
    "incident_reported": false,
    "last_timestamp": "2026-03-02T10:18:25Z"
  },
  "indexing_free": {
    "consecutive_failures": 0,
    "incident_reported": false,
    "last_timestamp": "2026-03-02T10:03:50Z"
  },
  "indexing_pro": {
    "consecutive_failures": 0,
    "incident_reported": false,
    "last_timestamp": "2026-03-02T10:03:51Z"
  },
  "webhook_free": {
    "consecutive_failures": 0,
    "incident_reported": false,
    "last_timestamp": "2026-03-02T10:03:56Z"
  },
  "webhook_pro": {
    "consecutive_failures": 0,
    "incident_reported": false,
    "last_timestamp": "2026-03-02T10:03:59Z"
  }
}