{
  "web_ui": {
    "consecutive_failures": 0,
    "incident_reported": false,
    "last_timestamp": "2026-02-26T05:15:21Z"
  },
  "api": {
    "consecutive_failures": 0,
    "incident_reported": false,
    "last_timestamp": "2026-02-26T05:15:23Z"
  },
  "sandbox": {
    "consecutive_failures": 0,
    "incident_reported": false,
    "last_timestamp": "2026-02-26T05:15:31Z"
  },
  "plugin": {
    "consecutive_failures": 2,
    "incident_reported": true,
    "last_timestamp": "2026-02-26T05:15:45Z"
  },
  "retrieve": {
    "consecutive_failures": 3,
    "incident_reported": true,
    "last_timestamp": "2026-02-26T05:16:03Z"
  },
  "indexing_pro": {
    "consecutive_failures": 1,
    "incident_reported": false,
    "last_timestamp": "2026-02-26T05:02:28Z"
  },
  "webhook_free": {
    "consecutive_failures": 0,
    "incident_reported": false,
    "last_timestamp": "2026-02-26T05:02:29Z"
  },
  "webhook_pro": {
    "consecutive_failures": 0,
    "incident_reported": false,
    "last_timestamp": "2026-02-26T05:02:51Z"
  },
  "indexing_free": {
    "consecutive_failures": 1,
    "incident_reported": false,
    "last_timestamp": "2026-02-26T05:02:03Z"
  }
}