{
  "web_ui": {
    "consecutive_failures": 0,
    "incident_reported": false,
    "last_timestamp": "2026-03-30T15:00:47Z"
  },
  "api": {
    "consecutive_failures": 0,
    "incident_reported": false,
    "last_timestamp": "2026-03-30T15:00:48Z"
  },
  "sandbox": {
    "consecutive_failures": 0,
    "incident_reported": false,
    "last_timestamp": "2026-03-30T15:00:52Z"
  },
  "plugin": {
    "consecutive_failures": 0,
    "incident_reported": false,
    "last_timestamp": "2026-03-30T15:00:55Z"
  },
  "retrieve": {
    "consecutive_failures": 0,
    "incident_reported": false,
    "last_timestamp": "2026-03-30T15:01:01Z"
  },
  "indexing_free": {
    "consecutive_failures": 0,
    "incident_reported": false,
    "last_timestamp": "2026-03-30T14:45:34Z"
  },
  "indexing_pro": {
    "consecutive_failures": 0,
    "incident_reported": false,
    "last_timestamp": "2026-03-30T14:45:35Z"
  },
  "webhook_free": {
    "consecutive_failures": 13,
    "incident_reported": true,
    "last_timestamp": "2026-03-30T15:01:05Z"
  },
  "webhook_pro": {
    "consecutive_failures": 13,
    "incident_reported": true,
    "last_timestamp": "2026-03-30T15:01:05Z"
  }
}