{
  "web_ui": {
    "consecutive_failures": 0,
    "incident_reported": false,
    "last_timestamp": "2026-02-26T06:15:25Z"
  },
  "api": {
    "consecutive_failures": 0,
    "incident_reported": false,
    "last_timestamp": "2026-02-26T06:15:26Z"
  },
  "sandbox": {
    "consecutive_failures": 0,
    "incident_reported": false,
    "last_timestamp": "2026-02-26T06:15:28Z"
  },
  "plugin": {
    "consecutive_failures": 0,
    "incident_reported": false,
    "last_timestamp": "2026-02-26T06:15:41Z"
  },
  "retrieve": {
    "consecutive_failures": 0,
    "incident_reported": false,
    "last_timestamp": "2026-02-26T06:15:51Z"
  },
  "indexing_pro": {
    "consecutive_failures": 3,
    "incident_reported": true,
    "last_timestamp": "2026-02-26T06:16:22Z"
  },
  "webhook_free": {
    "consecutive_failures": 0,
    "incident_reported": false,
    "last_timestamp": "2026-02-26T06:02:18Z"
  },
  "webhook_pro": {
    "consecutive_failures": 0,
    "incident_reported": false,
    "last_timestamp": "2026-02-26T06:02:41Z"
  },
  "indexing_free": {
    "consecutive_failures": 3,
    "incident_reported": true,
    "last_timestamp": "2026-02-26T06:02:04Z"
  }
}