{
  "web_ui": {
    "consecutive_failures": 0,
    "incident_reported": false,
    "last_timestamp": "2026-03-31T03:30:32Z"
  },
  "api": {
    "consecutive_failures": 0,
    "incident_reported": false,
    "last_timestamp": "2026-03-31T03:30:32Z"
  },
  "sandbox": {
    "consecutive_failures": 0,
    "incident_reported": false,
    "last_timestamp": "2026-03-31T03:30:34Z"
  },
  "plugin": {
    "consecutive_failures": 0,
    "incident_reported": false,
    "last_timestamp": "2026-03-31T03:30:37Z"
  },
  "retrieve": {
    "consecutive_failures": 0,
    "incident_reported": false,
    "last_timestamp": "2026-03-31T03:30:45Z"
  },
  "indexing_free": {
    "consecutive_failures": 0,
    "incident_reported": false,
    "last_timestamp": "2026-03-31T03:15:38Z"
  },
  "indexing_pro": {
    "consecutive_failures": 0,
    "incident_reported": false,
    "last_timestamp": "2026-03-31T03:15:39Z"
  },
  "webhook_free": {
    "consecutive_failures": 0,
    "incident_reported": false,
    "last_timestamp": "2026-03-31T03:15:46Z"
  },
  "webhook_pro": {
    "consecutive_failures": 0,
    "incident_reported": false,
    "last_timestamp": "2026-03-31T03:15:55Z"
  }
}