{
  "web_ui": {
    "consecutive_failures": 0,
    "incident_reported": false,
    "last_timestamp": "2026-04-24T16:15:29Z"
  },
  "api": {
    "consecutive_failures": 0,
    "incident_reported": false,
    "last_timestamp": "2026-04-24T16:15:30Z"
  },
  "sandbox": {
    "consecutive_failures": 0,
    "incident_reported": false,
    "last_timestamp": "2026-04-24T16:15:31Z"
  },
  "plugin": {
    "consecutive_failures": 0,
    "incident_reported": false,
    "last_timestamp": "2026-04-24T16:15:34Z"
  },
  "retrieve": {
    "consecutive_failures": 0,
    "incident_reported": false,
    "last_timestamp": "2026-04-24T16:15:38Z"
  },
  "indexing_free": {
    "consecutive_failures": 0,
    "incident_reported": false,
    "last_timestamp": "2026-04-24T16:01:02Z"
  },
  "indexing_pro": {
    "consecutive_failures": 0,
    "incident_reported": false,
    "last_timestamp": "2026-04-24T16:01:03Z"
  },
  "webhook_free": {
    "consecutive_failures": 0,
    "incident_reported": false,
    "last_timestamp": "2026-04-24T16:01:09Z"
  },
  "webhook_pro": {
    "consecutive_failures": 0,
    "incident_reported": false,
    "last_timestamp": "2026-04-24T16:01:10Z"
  }
}