{
  "web_ui": {
    "consecutive_failures": 0,
    "incident_reported": false,
    "last_timestamp": "2026-03-01T05:30:32Z"
  },
  "api": {
    "consecutive_failures": 0,
    "incident_reported": false,
    "last_timestamp": "2026-03-01T05:30:32Z"
  },
  "sandbox": {
    "consecutive_failures": 0,
    "incident_reported": false,
    "last_timestamp": "2026-03-01T05:30:33Z"
  },
  "plugin": {
    "consecutive_failures": 0,
    "incident_reported": false,
    "last_timestamp": "2026-03-01T05:30:37Z"
  },
  "retrieve": {
    "consecutive_failures": 0,
    "incident_reported": false,
    "last_timestamp": "2026-03-01T05:30:40Z"
  },
  "indexing_free": {
    "consecutive_failures": 0,
    "incident_reported": false,
    "last_timestamp": "2026-03-01T05:15:33Z"
  },
  "indexing_pro": {
    "consecutive_failures": 0,
    "incident_reported": false,
    "last_timestamp": "2026-03-01T05:15:42Z"
  },
  "webhook_free": {
    "consecutive_failures": 0,
    "incident_reported": false,
    "last_timestamp": "2026-03-01T05:15:47Z"
  },
  "webhook_pro": {
    "consecutive_failures": 0,
    "incident_reported": false,
    "last_timestamp": "2026-03-01T05:15:50Z"
  }
}