{
  "web_ui": {
    "consecutive_failures": 0,
    "incident_reported": false,
    "last_timestamp": "2026-06-04T22:45:23Z"
  },
  "api": {
    "consecutive_failures": 0,
    "incident_reported": false,
    "last_timestamp": "2026-06-04T22:45:24Z"
  },
  "sandbox": {
    "consecutive_failures": 0,
    "incident_reported": false,
    "last_timestamp": "2026-06-04T22:45:25Z"
  },
  "plugin": {
    "consecutive_failures": 0,
    "incident_reported": false,
    "last_timestamp": "2026-06-04T22:45:31Z"
  },
  "retrieve": {
    "consecutive_failures": 0,
    "incident_reported": false,
    "last_timestamp": "2026-06-04T22:45:36Z"
  },
  "indexing_free": {
    "consecutive_failures": 0,
    "incident_reported": false,
    "last_timestamp": "2026-06-04T22:30:44Z"
  },
  "indexing_pro": {
    "consecutive_failures": 0,
    "incident_reported": false,
    "last_timestamp": "2026-06-04T22:30:45Z"
  },
  "webhook_free": {
    "consecutive_failures": 20,
    "incident_reported": true,
    "last_timestamp": "2026-06-04T22:31:16Z"
  },
  "webhook_pro": {
    "consecutive_failures": 57,
    "incident_reported": true,
    "last_timestamp": "2026-06-04T22:46:20Z"
  }
}