{
  "web_ui": {
    "consecutive_failures": 0,
    "incident_reported": false,
    "last_timestamp": "2026-05-04T17:30:36Z"
  },
  "api": {
    "consecutive_failures": 0,
    "incident_reported": false,
    "last_timestamp": "2026-05-04T17:30:37Z"
  },
  "sandbox": {
    "consecutive_failures": 0,
    "incident_reported": false,
    "last_timestamp": "2026-05-04T17:30:38Z"
  },
  "plugin": {
    "consecutive_failures": 0,
    "incident_reported": false,
    "last_timestamp": "2026-05-04T17:30:42Z"
  },
  "retrieve": {
    "consecutive_failures": 0,
    "incident_reported": false,
    "last_timestamp": "2026-05-04T17:30:52Z"
  },
  "indexing_free": {
    "consecutive_failures": 0,
    "incident_reported": false,
    "last_timestamp": "2026-05-04T17:15:32Z"
  },
  "indexing_pro": {
    "consecutive_failures": 0,
    "incident_reported": false,
    "last_timestamp": "2026-05-04T17:15:33Z"
  },
  "webhook_free": {
    "consecutive_failures": 0,
    "incident_reported": false,
    "last_timestamp": "2026-05-04T17:15:39Z"
  },
  "webhook_pro": {
    "consecutive_failures": 0,
    "incident_reported": false,
    "last_timestamp": "2026-05-04T17:15:49Z"
  }
}