{
  "web_ui": {
    "consecutive_failures": 0,
    "incident_reported": false,
    "last_timestamp": "2026-06-18T15:15:37Z"
  },
  "api": {
    "consecutive_failures": 0,
    "incident_reported": false,
    "last_timestamp": "2026-06-18T15:15:38Z"
  },
  "sandbox": {
    "consecutive_failures": 0,
    "incident_reported": false,
    "last_timestamp": "2026-06-18T15:15:38Z"
  },
  "plugin": {
    "consecutive_failures": 0,
    "incident_reported": false,
    "last_timestamp": "2026-06-18T15:15:43Z"
  },
  "retrieve": {
    "consecutive_failures": 0,
    "incident_reported": false,
    "last_timestamp": "2026-06-18T15:15:46Z"
  },
  "indexing_free": {
    "consecutive_failures": 0,
    "incident_reported": false,
    "last_timestamp": "2026-06-18T15:01:07Z"
  },
  "indexing_pro": {
    "consecutive_failures": 0,
    "incident_reported": false,
    "last_timestamp": "2026-06-18T15:01:08Z"
  },
  "webhook_free": {
    "consecutive_failures": 0,
    "incident_reported": false,
    "last_timestamp": "2026-06-18T15:01:09Z"
  },
  "webhook_pro": {
    "consecutive_failures": 0,
    "incident_reported": false,
    "last_timestamp": "2026-06-18T15:01:11Z"
  }
}